dbx_utils/__init__.py
dbx_utils/folder.py
dbx_utils-0.3.2.dist-info/METADATA
dbx_utils-0.3.2.dist-info/WHEEL
dbx_utils-0.3.2.dist-info/top_level.txt
dbx_utils-0.3.2.dist-info/RECORD
