Metadata-Version: 2.1
Name: dbx_utils
Version: 0.3.2
Summary: A utility package for managing Databricks folders and permissions
Author: Ranjit Maity
Author-email: ranjitmaity95@gmail.com
Project-URL: Documentation, https://github.com/RanjitM007/dbx_utils/wiki
Project-URL: Source, https://github.com/RanjitM007/dbx_utils
Project-URL: Tracker, https://github.com/RanjitM007/dbx_utils/issues
Classifier: Programming Language :: Python :: 3
Classifier: License :: OSI Approved :: MIT License
Classifier: Operating System :: OS Independent
Requires-Python: >=3.6
Requires-Dist: requests
Requires-Dist: databricks-api
